birdbrain/__init__.py
birdbrain/constant.py
birdbrain/device.py
birdbrain/exception.py
birdbrain/finch.py
birdbrain/finch_input.py
birdbrain/finch_output.py
birdbrain/hummingbird.py
birdbrain/hummingbird_input.py
birdbrain/hummingbird_output.py
birdbrain/microbit.py
birdbrain/microbit_input.py
birdbrain/microbit_output.py
birdbrain/request.py
birdbrain/state.py
birdbrain/tasks.py
birdbrain/utility.py
birdbrain_python_library_2-0.10.4.dist-info/METADATA
birdbrain_python_library_2-0.10.4.dist-info/WHEEL
birdbrain_python_library_2-0.10.4.dist-info/licenses/AUTHORS.rst
birdbrain_python_library_2-0.10.4.dist-info/licenses/LICENSE
birdbrain_python_library_2-0.10.4.dist-info/RECORD
